README.md
setup.py
azsaprfc/__init__.py
azsaprfc/saprfc.py
azsaprfc.egg-info/PKG-INFO
azsaprfc.egg-info/SOURCES.txt
azsaprfc.egg-info/dependency_links.txt
azsaprfc.egg-info/top_level.txt