Metadata-Version: 2.1
Name: azsaprfc
Version: 1.1.1
Summary: SAP Tools for python
Author: AndyZhu
Author-email: andyzhu@live.com
